objfreeze/__init__.py
objfreeze-0.1.0b0.dist-info/LICENCE
objfreeze-0.1.0b0.dist-info/METADATA
objfreeze-0.1.0b0.dist-info/WHEEL
objfreeze-0.1.0b0.dist-info/top_level.txt
objfreeze-0.1.0b0.dist-info/RECORD
