Metadata-Version: 2.1
Name: objfreeze
Version: 0.1.0b0
Summary: Function to convert data into freezed (immutable) version
Home-page: https://gitlab.com/vitaly.burovoy/py-objfreeze
Author: Vitaly Burovoy
Author-email: vitaly.burovoy@gmail.com
License: BSD
Platform: OS-independent
Classifier: Development Status :: 4 - Beta
Classifier: Intended Audience :: Developers
Classifier: License :: OSI Approved :: BSD License
Classifier: Natural Language :: English
Classifier: Operating System :: OS Independent
Classifier: Programming Language :: Python :: 3 :: Only
Classifier: Programming Language :: Python :: 3.5
Classifier: Programming Language :: Python :: 3.6
Classifier: Topic :: Software Development :: Libraries
